visualizers/__init__.py
visualizers/version.py
visualizers-0.0.1.dist-info/licenses/LICENSE
visualizers-0.0.1.dist-info/METADATA
visualizers-0.0.1.dist-info/WHEEL
visualizers-0.0.1.dist-info/top_level.txt
visualizers-0.0.1.dist-info/RECORD
