Metadata-Version: 2.4
Name: visualizers
Version: 0.0.1
Summary: AI inference visualizers.
Author-email: "NatML Inc." <hi@muna.ai>
License:                                  Apache License
Project-URL: Homepage, https://visualizers.dev
Project-URL: Documentation, https://docs.visualizers.dev
Project-URL: Source, https://github.com/muna-ai/visualizers-py
Project-URL: Changelog, https://github.com/muna-ai/visualizers-py/blob/main/Changelog.md
Classifier: Programming Language :: Python :: 3
Classifier: License :: OSI Approved :: Apache Software License
Classifier: Operating System :: OS Independent
Classifier: Topic :: Scientific/Engineering :: Image Recognition
Classifier: Topic :: Software Development :: Libraries
Requires-Python: >=3.11
License-File: LICENSE
Dynamic: license-file
